setup.py
torrents_dispatcher/__init__.py
torrents_dispatcher/__main__.py
torrents_dispatcher/safeutil.py
torrents_dispatcher/torrents_dispatcher.py
torrents_dispatcher.egg-info/PKG-INFO
torrents_dispatcher.egg-info/SOURCES.txt
torrents_dispatcher.egg-info/dependency_links.txt
torrents_dispatcher.egg-info/entry_points.txt
torrents_dispatcher.egg-info/requires.txt
torrents_dispatcher.egg-info/top_level.txt