Metadata-Version: 1.1
Name: torrents-dispatcher
Version: 0.0.4
Summary: Dispatch your torrents between multiple torrents clients
Home-page: https://github.com/Anthony25/torrents_dispatcher
Author: Anthony25 <Anthony Ruhier>
Author-email: anthony.ruhier@gmail.com
License: Simplified BSD
Keywords: torrent
Platform: UNKNOWN
Classifier: Operating System :: POSIX :: Linux
Classifier: Programming Language :: Python :: 3 :: Only
Classifier: License :: OSI Approved :: BSD License
